oxford_matplotlib_theme/__init__.py
oxford_matplotlib_theme/colors.py
oxford_matplotlib_theme/presets.py
oxford_matplotlib_theme/py.typed
oxford_matplotlib_theme/styles.py
oxford_matplotlib_theme/utils.py
oxford_matplotlib_theme-1.0.0.dist-info/licenses/LICENSE
oxford_matplotlib_theme-1.0.0.dist-info/METADATA
oxford_matplotlib_theme-1.0.0.dist-info/WHEEL
oxford_matplotlib_theme-1.0.0.dist-info/top_level.txt
oxford_matplotlib_theme-1.0.0.dist-info/RECORD
