Metadata-Version: 2.4
Name: oxford_matplotlib_theme
Version: 1.0.0
Summary: Matplotlib visualization theme following Official Oxford University colors and styling.
Author-email: Sami Adnan <sami.adnan@phc.ox.ac.uk>
License-Expression: MIT
Project-URL: Homepage, https://github.com/sami5001/oxford-matplotlib-theme
Project-URL: Documentation, https://github.com/sami5001/oxford-matplotlib-theme#readme
Project-URL: Repository, https://github.com/sami5001/oxford-matplotlib-theme
Project-URL: Issues, https://github.com/sami5001/oxford-matplotlib-theme/issues
Keywords: oxford,matplotlib,theme,visualization,plotting,academic,publication
Classifier: Development Status :: 4 - Beta
Classifier: Intended Audience :: Science/Research
Classifier: Programming Language :: Python :: 3
Classifier: Programming Language :: Python :: 3.8
Classifier: Programming Language :: Python :: 3.9
Classifier: Programming Language :: Python :: 3.10
Classifier: Programming Language :: Python :: 3.11
Classifier: Programming Language :: Python :: 3.12
Classifier: Topic :: Scientific/Engineering :: Visualization
Classifier: Topic :: Scientific/Engineering :: Medical Science Apps.
Requires-Python: >=3.8
License-File: LICENSE
Requires-Dist: matplotlib>=3.5.0
Requires-Dist: numpy>=1.21.0
Provides-Extra: dev
Requires-Dist: pytest>=7.0.0; extra == "dev"
Requires-Dist: pytest-cov>=3.0.0; extra == "dev"
Requires-Dist: black>=22.0.0; extra == "dev"
Requires-Dist: flake8>=4.0.0; extra == "dev"
Requires-Dist: mypy>=0.950; extra == "dev"
Provides-Extra: examples
Requires-Dist: pandas>=1.3.0; extra == "examples"
Requires-Dist: scikit-learn>=1.0.0; extra == "examples"
Requires-Dist: scipy>=1.7.0; extra == "examples"
Provides-Extra: all
Requires-Dist: oxford_matplotlib_theme[dev,examples]; extra == "all"
Dynamic: license-file
